<?xml version="1.0" encoding="utf-8"?>
<varlist name="Settings">
	<varlist name="MapViewOptions">
		<varlist name="HF">
			<string name="IndexedPalette">Monochrome</string>
		</varlist>
		<varlist name="WS">
			<string name="IndexedPalette">Thermal</string>
		</varlist>
		<varlist name="SH">
			<string name="IndexedPalette">InverseBoolean</string>
		</varlist>
	</varlist>
	<varlist name="HF">
		<float name="HorizScale">3</float>
		<int name="nx">1025</int>
		<int name="ny">1025</int>
	</varlist>
	<varlist name="Sapphire">
		<varlist name="PathList">		</varlist>
		<varlist name="TeleportList">		</varlist>
	</varlist>
	<int name="SettingsVersion">2540</int>
</varlist>
